sardana/__init__.py
sardana/conftest.py
sardana/release.py
sardana/sardanaattribute.py
sardana/sardanabase.py
sardana/sardanabuffer.py
sardana/sardanacontainer.py
sardana/sardanacustomsettings.py
sardana/sardanadefs.py
sardana/sardanaevent.py
sardana/sardanaexception.py
sardana/sardanalock.py
sardana/sardanamanager.py
sardana/sardanameta.py
sardana/sardanamodulemanager.py
sardana/sardanathreadpool.py
sardana/sardanautils.py
sardana/sardanavalue.py
sardana/cli/__init__.py
sardana/cli/cli.py
sardana/macroserver/__init__.py
sardana/macroserver/basetypes.py
sardana/macroserver/macro.py
sardana/macroserver/macro_template.txt
sardana/macroserver/macroserver.py
sardana/macroserver/msbase.py
sardana/macroserver/mscontainer.py
sardana/macroserver/msdoor.py
sardana/macroserver/msenvmanager.py
sardana/macroserver/msexception.py
sardana/macroserver/msmacromanager.py
sardana/macroserver/msmanager.py
sardana/macroserver/msmetamacro.py
sardana/macroserver/msmetarecorder.py
sardana/macroserver/msoptions.py
sardana/macroserver/msparameter.py
sardana/macroserver/msrecordermanager.py
sardana/macroserver/mstypemanager.py
sardana/macroserver/macros/__init__.py
sardana/macroserver/macros/communication.py
sardana/macroserver/macros/demo.py
sardana/macroserver/macros/discrete.py
sardana/macroserver/macros/env.py
sardana/macroserver/macros/expconf.py
sardana/macroserver/macros/expert.py
sardana/macroserver/macros/h5storage.py
sardana/macroserver/macros/hkl.py
sardana/macroserver/macros/ioregister.py
sardana/macroserver/macros/lists.py
sardana/macroserver/macros/mca.py
sardana/macroserver/macros/scan.py
sardana/macroserver/macros/sequence.py
sardana/macroserver/macros/standard.py
sardana/macroserver/macros/examples/__init__.py
sardana/macroserver/macros/examples/acquisition.py
sardana/macroserver/macros/examples/debug.py
sardana/macroserver/macros/examples/funcs.py
sardana/macroserver/macros/examples/hooks.py
sardana/macroserver/macros/examples/motion.py
sardana-3.6.0.dist-info/licenses/LICENSE
sardana-3.6.0.dist-info/METADATA
sardana-3.6.0.dist-info/WHEEL
sardana-3.6.0.dist-info/entry_points.txt
sardana-3.6.0.dist-info/top_level.txt
sardana-3.6.0.dist-info/RECORD
